promt_quest/functions.py
promt_quest/nnopt1.py
promt_quest/nnopt2.py
promt_quest/nopt1.py
promt_quest/nopt2.py
promt_quest/nopt3.py
promt_quest/nopt4.py
promt_quest/nopt5.py
promt_quest/nopt6.py
promt_quest/opt1.py
promt_quest/opt2.py
promt_quest/opt3.py
promt_quest/path.txt
promt_quest/start.py
promt_quest-0.1.0.dist-info/LICENSE
promt_quest-0.1.0.dist-info/METADATA
promt_quest-0.1.0.dist-info/WHEEL
promt_quest-0.1.0.dist-info/RECORD
