Metadata-Version: 2.3
Name: promt-quest
Version: 0.1.0
Summary: A fun game choose your own adventure game in cli
Author: kush
Author-email: kushmdesai@icloud.com
Requires-Python: >=3.13
Classifier: Programming Language :: Python :: 3
Classifier: Programming Language :: Python :: 3.13
